fsk/__init__.py
fsk/__main__.py
fsk_cli-1.0.dist-info/METADATA
fsk_cli-1.0.dist-info/WHEEL
fsk_cli-1.0.dist-info/entry_points.txt
fsk_cli-1.0.dist-info/top_level.txt
fsk_cli-1.0.dist-info/RECORD
